{
  "produto_buscado": "ESTOFADO PARANA MOSCOU 3X2 LUG",
  "timestamp": "2026-03-05 11:43:15",
  "produtos_patrocinados": [
    {
      "nome": "Conjunto de Sofá 2 e 3 Lugares Moscou Flash Paraná | Cinza",
      "preco": "R$ 1.319,90",
      "loja": "Lojasmm",
      "link": "https://www.lojasmm.com/conjunto-de-sofa-parana-moscou-flash-3-e-2-lugares/p?idsku=11433"
    },
    {
      "nome": "Conjunto de Sofá 2 e 3 Lugares Moscou Flash Paraná | Bege",
      "preco": "R$ 1.319,90",
      "loja": "Lojasmm",
      "link": "https://www.lojasmm.com/conjunto-de-sofa-parana-moscou-flash-3-e-2-lugares/p?idsku=11431"
    },
    {
      "nome": "Sofa Parana Moscou 3 E 2 Lugares, Cinza",
      "preco": "R$ 1.179,90",
      "loja": "Magazineluiza",
      "link": "https://www.magazineluiza.com.br/sofa-parana-moscou-3-e-2-lugares/p/deadjekecc/mo/coes/?&seller_id=lojasmm"
    },
    {
      "nome": "Conjunto de Sofá 2 e 3 Lugares Moscou Flash Paraná | Marrom",
      "preco": "R$ 1.319,90",
      "loja": "Lojasmm",
      "link": "https://www.lojasmm.com/conjunto-de-sofa-parana-moscou-flash-3-e-2-lugares/p?idsku=11434"
    },
    {
      "nome": "Conjunto Sofá 3 e 2 Lugares Veludo Lisboa Estofados Paraná Cinza/Asteca S/V",
      "preco": "R$ 1.399,90",
      "loja": "Multiloja",
      "link": "https://www.multiloja.com.br/conjunto-sofa-3-e-2-lugares-veludo-lisboa-estofados-parana-23097/p?idsku=23265"
    },
    {
      "nome": "Sofa Parana Moscou 3 E 2 Lugares - Cinza",
      "preco": "R$ 1.109,90",
      "loja": "Casasbahia",
      "link": "https://www.casasbahia.com.br/sofa-parana-moscou-3-e-2-lugares/p/1560331743?utm_medium=Cpc&utm_source=google_freelisting&IdSku=1560331743&idLojista=88205&tipoLojista=3P"
    },
    {
      "nome": "Conjunto de Sofá Paraná Fluence 3 e 2 Lugares com Estrutura Reforçada e Assento Confortável Conjunto de Sofá Paraná Fluence 3 e 2 Lugares | Marrom (S",
      "preco": "R$ 1.299,90",
      "loja": "Lojasmm",
      "link": "https://www.lojasmm.com/conjunto-de-sofa-parana-fluence-3-e-2-lugares-/p?idsku=1559"
    },
    {
      "nome": "Conjunto de Sofá Paraná Paris 3 e 2 Lugares | Marrom",
      "preco": "R$ 1.419,90",
      "loja": "Lojasmm",
      "link": "https://www.lojasmm.com/conjunto-de-sofa-parana-paris-3-e-2-lugares/p?idsku=1676"
    },
    {
      "nome": "Conjunto Sofá 3x2 Lugares Moscou 2763 Amêndoa - Lucca",
      "preco": "R$ 2.499,00",
      "loja": "Koerich",
      "link": "https://www.koerich.com.br/p/conjunto-sofa-3x2-lugares-moscou-2763-amendoa-lucca/4333507"
    },
    {
      "nome": "Conjunto de Sofá Paraná Fluence 3 e 2 Lugares com Estrutura Reforçada e Assento Confortável Conjunto de Sofá Paraná Fluence 3 e 2 Lugares | Cinza (S/",
      "preco": "R$ 1.299,90",
      "loja": "Lojasmm",
      "link": "https://www.lojasmm.com/conjunto-de-sofa-parana-fluence-3-e-2-lugares-/p?idsku=1558"
    },
    {
      "nome": "Sofa Parana Moscou 3 E 2 Lugares, Marrom",
      "preco": "R$ 1.179,90",
      "loja": "Magazineluiza",
      "link": "https://www.magazineluiza.com.br/sofa-parana-moscou-3-e-2-lugares/p/gb11gd5755/mo/coes/?&seller_id=lojasmm"
    },
    {
      "nome": "Conjunto Sofá 3 e 2 Lugares Veludo Lisboa Estofados Paraná Marrom/Asteca S/V",
      "preco": "R$ 1.399,90",
      "loja": "Multiloja",
      "link": "https://www.multiloja.com.br/conjunto-sofa-3-e-2-lugares-veludo-lisboa-estofados-parana-23097/p?idsku=23266"
    },
    {
      "nome": "Sofa Parana Moscou 3 E 2 Lugares",
      "preco": "R$ 1.232,70",
      "loja": "Madeiramadeira",
      "link": "https://www.madeiramadeira.com.br/sofa-parana-moscou-3-e-2-lugares-663521607.html?origem=pla-663521607&seller=15264"
    },
    {
      "nome": "Conjunto de Sofá 2 e 3 Lugares Sandero Paraná | Marrom",
      "preco": "R$ 1.219,90",
      "loja": "Lojasmm",
      "link": "https://www.lojasmm.com/conjunto-de-sofa-parana-sandero-3-e-2-lugares/p?idsku=1572"
    },
    {
      "nome": "Sofa Parana Moscou 3 E 2 Lugares Cor Bege Paraná",
      "preco": "R$ 1.219,90",
      "loja": "Mercado Livre",
      "link": "https://www.mercadolivre.com.br/sofa-parana-moscou-3-e-2-lugares-cor-bege/p/MLB25457802?matt_tool=18956390&utm_source=google_shopping&utm_medium=organic&pdp_filters=item_id%3AMLB3403515657&from=gshop"
    },
    {
      "nome": "Sofa Moscou 3 E 2 Lugares 4075 Parana Marrom",
      "preco": "R$ 1.239,90",
      "loja": "Colombo",
      "link": "https://www.colombo.com.br/produto/Moveis-e-Decoracao/Sofa-Moscou-3-E-2-Lugares-4075-Parana-Marrom-Marrom?portal=8B36E9207C24C76E6719268E49201D94"
    },
    {
      "nome": "Conjunto Sofá 3 e 2 Lugares Paris Sued Flash",
      "preco": "R$ 899,90",
      "loja": "Amazon",
      "link": "https://www.amazon.com.br/Conjunto-Sof%C3%A1-Lugares-Paris-Flash/dp/B0C3RQMYMG?source=ps-sl-shoppingads-lpcontext&ref_=fplfs&psc=1&smid=A3N6KT05BBJSG1"
    },
    {
      "nome": "Conjunto de Sofá 2 e 3 Lugares Moscou Flash Paraná | Azul",
      "preco": "R$ 1.319,90",
      "loja": "Lojasmm",
      "link": "https://www.lojasmm.com/conjunto-de-sofa-parana-moscou-flash-3-e-2-lugares/p?idsku=11432"
    },
    {
      "nome": "Conjunto Sofá 3 e 2 Lugares Veludo Lisboa Estofados Paraná Castor/Asteca S/V",
      "preco": "R$ 1.399,90",
      "loja": "Multiloja",
      "link": "https://www.multiloja.com.br/conjunto-sofa-3-e-2-lugares-veludo-lisboa-estofados-parana-23097/p?idsku=23264"
    },
    {
      "nome": "Conjunto De Sofá Paraná Azera 3 e 2 Lugares Courino | Marrom",
      "preco": "R$ 1.599,90",
      "loja": "Lojasmm",
      "link": "https://www.lojasmm.com/conjunto-de-sofa-parana-azera-3-e-2-lugares-courino-/p?idsku=1625"
    }
  ],
  "batch_id": "20260305_114127"
}